odoo/addons/hr_employee_relative/README.rst
odoo/addons/hr_employee_relative/__init__.py
odoo/addons/hr_employee_relative/__manifest__.py
odoo/addons/hr_employee_relative/data/data_relative_relation.xml
odoo/addons/hr_employee_relative/i18n/fr.po
odoo/addons/hr_employee_relative/i18n/hr_employee_relative.pot
odoo/addons/hr_employee_relative/migrations/12.0.1.0.0/post-migration.py
odoo/addons/hr_employee_relative/models/__init__.py
odoo/addons/hr_employee_relative/models/hr_employee.py
odoo/addons/hr_employee_relative/models/hr_employee_relative.py
odoo/addons/hr_employee_relative/models/hr_employee_relative_relation.py
odoo/addons/hr_employee_relative/readme/CONTRIBUTORS.rst
odoo/addons/hr_employee_relative/readme/DESCRIPTION.rst
odoo/addons/hr_employee_relative/security/ir.model.access.csv
odoo/addons/hr_employee_relative/static/description/icon.png
odoo/addons/hr_employee_relative/static/description/index.html
odoo/addons/hr_employee_relative/tests/__init__.py
odoo/addons/hr_employee_relative/tests/test_hr_employee_relatives.py
odoo/addons/hr_employee_relative/views/hr_employee.xml
odoo/addons/hr_employee_relative/views/hr_employee_relative.xml
odoo12_addon_hr_employee_relative-12.0.1.1.0.dist-info/METADATA
odoo12_addon_hr_employee_relative-12.0.1.1.0.dist-info/WHEEL
odoo12_addon_hr_employee_relative-12.0.1.1.0.dist-info/top_level.txt
odoo12_addon_hr_employee_relative-12.0.1.1.0.dist-info/RECORD
